kgdd/__init__.py
kgdd/__main__.py
kgdd/kg_reader.py
kgdd/kg_tester.py
kgdd/logger.py
kgdd/test.py
kgdd/test_file.py
kgdd/test_file_parser.py
kgdd-0.1.1.dist-info/METADATA
kgdd-0.1.1.dist-info/WHEEL
kgdd-0.1.1.dist-info/entry_points.txt
kgdd-0.1.1.dist-info/top_level.txt
kgdd-0.1.1.dist-info/RECORD
