Metadata-Version: 2.1
Name: kgdd
Version: 0.1.1
Summary: UNKNOWN
Home-page: https://github.com/ccolonna/kgdd
License: UNKNOWN
Platform: UNKNOWN
Requires-Python: >=3.5
Requires-Dist: colorama (==0.4.4)
Requires-Dist: isodate (==0.6.0)
Requires-Dist: pyparsing (==2.4.7)
Requires-Dist: rdflib (==6.0.1)
Requires-Dist: six (==1.16.0)
